setup.cfg
setup.py
src/cli/__init__.py
src/kirby_transform/__init__.py
src/kirby_transform.egg-info/PKG-INFO
src/kirby_transform.egg-info/SOURCES.txt
src/kirby_transform.egg-info/dependency_links.txt
src/kirby_transform.egg-info/entry_points.txt
src/kirby_transform.egg-info/requires.txt
src/kirby_transform.egg-info/top_level.txt
src/kirby_transform/outputs/__init__.py
src/kirby_transform/outputs/influx2/__init__.py
src/kirby_transform/outputs/influx2/process.py
src/kirby_transform/outputs/timestream/__init__.py
src/kirby_transform/outputs/timestream/process.py
src/kirby_transform/pipelines/__init__.py
src/kirby_transform/pipelines/aws/__init__.py
src/kirby_transform/pipelines/aws/env_vars.py
src/kirby_transform/processor/__init__.py
src/kirby_transform/processor/processor.py
src/kirby_transform/release/__init__.py
src/kirby_transform/release/release_helpers.py
src/kirby_transform/schema/__init__.py
src/kirby_transform/schema/validator.py
src/kirby_transform/schema/input/__init__.py
src/kirby_transform/schema/input/schema.py
src/kirby_transform/test/__init__.py
src/kirby_transform/test/helper.py