Metadata-Version: 2.1
Name: kirby-transform
Version: 0.1.3
Summary: Transformation middleware for Project Kirby
Home-page: https://github.com/SrzStephen/Kirby-Transform
Author: Stephen Mott
License: UNKNOWN
Platform: linux
Classifier: Development Status :: 3 - Alpha
Classifier: Intended Audience :: Developers
Classifier: Topic :: Software Development :: Libraries
Classifier: Programming Language :: Python :: 3.7
Requires-Python: >=3.5
